[
  {
    "day": "2026-03-09",
    "initiated_amount": 18470.054758540766,
    "initiated_users": 14,
    "queue_amount": 18470.054758540762,
    "unlock_amount": 0,
    "vvv_price_usd": null,
    "trade_volume_usd": 1256473.3781043242,
    "staked_amount": 247099.87852545636,
    "staked_users": 127,
    "buy_volume_usd": 531451.3080591131,
    "sell_volume_usd": 725022.0700452109
  },
  {
    "day": "2026-03-10",
    "initiated_amount": 27927.86469106592,
    "initiated_users": 29,
    "queue_amount": 46397.919449606685,
    "unlock_amount": 0,
    "vvv_price_usd": null,
    "trade_volume_usd": 6483788.0531975925,
    "staked_amount": 58278.472734753814,
    "staked_users": 349,
    "buy_volume_usd": 3441009.5356370886,
    "sell_volume_usd": 3042778.5175605044
  },
  {
    "day": "2026-03-11",
    "initiated_amount": 30993.554896501493,
    "initiated_users": 20,
    "queue_amount": 77391.4743461082,
    "unlock_amount": 0,
    "vvv_price_usd": null,
    "trade_volume_usd": 5700944.338604848,
    "staked_amount": 80366.15181903147,
    "staked_users": 280,
    "buy_volume_usd": 3097279.02842645,
    "sell_volume_usd": 2603665.3101784005
  },
  {
    "day": "2026-03-12",
    "initiated_amount": 10211.540879384153,
    "initiated_users": 23,
    "queue_amount": 87603.01522549235,
    "unlock_amount": 0,
    "vvv_price_usd": null,
    "trade_volume_usd": 5313355.433175501,
    "staked_amount": 33115.82541710079,
    "staked_users": 302,
    "buy_volume_usd": 2876425.7879762957,
    "sell_volume_usd": 2436929.645199203
  },
  {
    "day": "2026-03-13",
    "initiated_amount": 141640.8373964229,
    "initiated_users": 32,
    "queue_amount": 229243.85262191528,
    "unlock_amount": 0,
    "vvv_price_usd": null,
    "trade_volume_usd": 12580886.559347142,
    "staked_amount": 56736.98509641668,
    "staked_users": 408,
    "buy_volume_usd": 6574182.758134829,
    "sell_volume_usd": 6006703.801212308
  },
  {
    "day": "2026-03-14",
    "initiated_amount": 15733.040691856562,
    "initiated_users": 28,
    "queue_amount": 244976.89331377178,
    "unlock_amount": 0,
    "vvv_price_usd": null,
    "trade_volume_usd": 5748468.087739896,
    "staked_amount": 132004.9741767422,
    "staked_users": 251,
    "buy_volume_usd": 3059428.6386407563,
    "sell_volume_usd": 2689039.4490991402
  },
  {
    "day": "2026-03-15",
    "initiated_amount": 150643.9336176149,
    "initiated_users": 21,
    "queue_amount": 395620.8269313867,
    "unlock_amount": 0,
    "vvv_price_usd": null,
    "trade_volume_usd": 5023101.4054185795,
    "staked_amount": 84819.01524737627,
    "staked_users": 271,
    "buy_volume_usd": 2064188.5976021409,
    "sell_volume_usd": 2958912.8078164365
  },
  {
    "day": "2026-03-16",
    "initiated_amount": 21662.433875682233,
    "initiated_users": 30,
    "queue_amount": 417283.2608070691,
    "unlock_amount": 18470.054758540766,
    "vvv_price_usd": null,
    "trade_volume_usd": 4292351.488656724,
    "staked_amount": 44608.81585710712,
    "staked_users": 283,
    "buy_volume_usd": 1856111.4463212963,
    "sell_volume_usd": 2436240.04233543
  },
  {
    "day": "2026-03-17",
    "initiated_amount": 11391.245276642187,
    "initiated_users": 17,
    "queue_amount": 410204.4513251705,
    "unlock_amount": 27927.864691065923,
    "vvv_price_usd": null,
    "trade_volume_usd": 6799163.0237574745,
    "staked_amount": 122267.00609556359,
    "staked_users": 274,
    "buy_volume_usd": 2337554.3090520706,
    "sell_volume_usd": 4461608.7147054
  },
  {
    "day": "2026-03-18",
    "initiated_amount": 71723.9484291951,
    "initiated_users": 25,
    "queue_amount": 454000.53506329976,
    "unlock_amount": 30993.554896501497,
    "vvv_price_usd": null,
    "trade_volume_usd": 6103695.058378244,
    "staked_amount": 87519.70880775414,
    "staked_users": 286,
    "buy_volume_usd": 2855135.489672342,
    "sell_volume_usd": 3248559.5687059034
  },
  {
    "day": "2026-03-19",
    "initiated_amount": 2555.0284258342663,
    "initiated_users": 12,
    "queue_amount": 425562.0085926326,
    "unlock_amount": 10211.540879384153,
    "vvv_price_usd": null,
    "trade_volume_usd": 4474681.756570756,
    "staked_amount": 40351.77209348081,
    "staked_users": 266,
    "buy_volume_usd": 2170908.1827161573,
    "sell_volume_usd": 2303773.5738545996
  },
  {
    "day": "2026-03-20",
    "initiated_amount": 5004.53368887814,
    "initiated_users": 17,
    "queue_amount": 420355.00140212657,
    "unlock_amount": 141640.8373964229,
    "vvv_price_usd": null,
    "trade_volume_usd": 4329887.86720103,
    "staked_amount": 30872.323595857924,
    "staked_users": 291,
    "buy_volume_usd": 2036177.888186037,
    "sell_volume_usd": 2293709.979014997
  },
  {
    "day": "2026-03-21",
    "initiated_amount": 3197.9029184707624,
    "initiated_users": 12,
    "queue_amount": 281912.06692417426,
    "unlock_amount": 15733.040691856562,
    "vvv_price_usd": null,
    "trade_volume_usd": 3850672.2928416263,
    "staked_amount": 39910.00892632068,
    "staked_users": 292,
    "buy_volume_usd": 2313719.5357845705,
    "sell_volume_usd": 1536952.7570570535
  },
  {
    "day": "2026-03-22",
    "initiated_amount": 2741.8577058833525,
    "initiated_users": 17,
    "queue_amount": 268920.88393820095,
    "unlock_amount": 150643.9336176149,
    "vvv_price_usd": null,
    "trade_volume_usd": 3878921.3429750204,
    "staked_amount": 117882.83772095233,
    "staked_users": 278,
    "buy_volume_usd": 1957356.3021542649,
    "sell_volume_usd": 1921565.040820755
  },
  {
    "day": "2026-03-23",
    "initiated_amount": 82695.5491666421,
    "initiated_users": 22,
    "queue_amount": 200972.49948722808,
    "unlock_amount": 21662.433875682233,
    "vvv_price_usd": null,
    "trade_volume_usd": 5149873.783291274,
    "staked_amount": 48083.24291303397,
    "staked_users": 306,
    "buy_volume_usd": 2288801.9799175686,
    "sell_volume_usd": 2861071.8033737084
  },
  {
    "day": "2026-03-24",
    "initiated_amount": 9863.737863976661,
    "initiated_users": 12,
    "queue_amount": 189173.80347552258,
    "unlock_amount": 11391.245276642187,
    "vvv_price_usd": null,
    "trade_volume_usd": 4181983.4245607047,
    "staked_amount": 29559.841427965726,
    "staked_users": 257,
    "buy_volume_usd": 2371647.055416241,
    "sell_volume_usd": 1810336.3691444655
  },
  {
    "day": "2026-03-25",
    "initiated_amount": 9877.387728841428,
    "initiated_users": 43,
    "queue_amount": 187659.94592772186,
    "unlock_amount": 71723.9484291951,
    "vvv_price_usd": null,
    "trade_volume_usd": 9422077.14502065,
    "staked_amount": 52227.657211626705,
    "staked_users": 363,
    "buy_volume_usd": 4818080.789437215,
    "sell_volume_usd": 4603996.355583443
  },
  {
    "day": "2026-03-26",
    "initiated_amount": 14921.601369467982,
    "initiated_users": 26,
    "queue_amount": 130857.5988679947,
    "unlock_amount": 2555.028425834266,
    "vvv_price_usd": null,
    "trade_volume_usd": 4393612.53330859,
    "staked_amount": 57583.18744998633,
    "staked_users": 263,
    "buy_volume_usd": 2271958.2982348506,
    "sell_volume_usd": 2121654.2350737383
  },
  {
    "day": "2026-03-27",
    "initiated_amount": 82994.02537203861,
    "initiated_users": 16,
    "queue_amount": 211296.59581419907,
    "unlock_amount": 5004.53368887814,
    "vvv_price_usd": null,
    "trade_volume_usd": 3928726.4595736736,
    "staked_amount": 51872.58924322892,
    "staked_users": 252,
    "buy_volume_usd": 1868604.7777506048,
    "sell_volume_usd": 2060121.681823068
  },
  {
    "day": "2026-03-28",
    "initiated_amount": 3352.8742566101087,
    "initiated_users": 13,
    "queue_amount": 209644.93638193104,
    "unlock_amount": 3197.9029184707624,
    "vvv_price_usd": null,
    "trade_volume_usd": 2846463.5893963412,
    "staked_amount": 56006.58003747201,
    "staked_users": 246,
    "buy_volume_usd": 1409548.6551124218,
    "sell_volume_usd": 1436914.9342839203
  },
  {
    "day": "2026-03-29",
    "initiated_amount": 3448.1349174666275,
    "initiated_users": 12,
    "queue_amount": 209895.16838092692,
    "unlock_amount": 2741.8577058833525,
    "vvv_price_usd": null,
    "trade_volume_usd": 2474717.9765128912,
    "staked_amount": 42869.111003439015,
    "staked_users": 219,
    "buy_volume_usd": 1361524.2988408566,
    "sell_volume_usd": 1113193.677672036
  },
  {
    "day": "2026-03-30",
    "initiated_amount": 7429.140195367652,
    "initiated_users": 17,
    "queue_amount": 214582.45087041115,
    "unlock_amount": 82695.54916664211,
    "vvv_price_usd": null,
    "trade_volume_usd": 6072255.71802316,
    "staked_amount": 61069.02848064957,
    "staked_users": 293,
    "buy_volume_usd": 3037802.791409153,
    "sell_volume_usd": 3034452.926614012
  },
  {
    "day": "2026-03-31",
    "initiated_amount": 12307.123016427158,
    "initiated_users": 16,
    "queue_amount": 144194.0247201963,
    "unlock_amount": 9863.737863976661,
    "vvv_price_usd": null,
    "trade_volume_usd": 6820722.90781225,
    "staked_amount": 34032.57054126618,
    "staked_users": 286,
    "buy_volume_usd": 3510738.5524648563,
    "sell_volume_usd": 3309984.355347401
  },
  {
    "day": "2026-04-01",
    "initiated_amount": 23758.584388912856,
    "initiated_users": 19,
    "queue_amount": 158088.8712451324,
    "unlock_amount": 9877.387728841428,
    "vvv_price_usd": null,
    "trade_volume_usd": 11446749.655031329,
    "staked_amount": 87791.64178473323,
    "staked_users": 381,
    "buy_volume_usd": 5814810.808969872,
    "sell_volume_usd": 5631938.846061444
  },
  {
    "day": "2026-04-02",
    "initiated_amount": 76136.52959528816,
    "initiated_users": 22,
    "queue_amount": 224348.01311157917,
    "unlock_amount": 14921.601369467982,
    "vvv_price_usd": null,
    "trade_volume_usd": 7962250.890546668,
    "staked_amount": 79560.08827164149,
    "staked_users": 342,
    "buy_volume_usd": 4251263.016325515,
    "sell_volume_usd": 3710987.8742211666
  },
  {
    "day": "2026-04-03",
    "initiated_amount": 3760.516996344441,
    "initiated_users": 20,
    "queue_amount": 213186.92873845567,
    "unlock_amount": 82994.02537203861,
    "vvv_price_usd": null,
    "trade_volume_usd": 4253162.331011411,
    "staked_amount": 51783.59266089642,
    "staked_users": 311,
    "buy_volume_usd": 2205301.8698314307,
    "sell_volume_usd": 2047860.461179981
  },
  {
    "day": "2026-04-04",
    "initiated_amount": 3056.8950164139515,
    "initiated_users": 20,
    "queue_amount": 133249.79838283092,
    "unlock_amount": 3352.8742566101087,
    "vvv_price_usd": null,
    "trade_volume_usd": 3022196.543474239,
    "staked_amount": 62872.4181411723,
    "staked_users": 271,
    "buy_volume_usd": 1375766.904046637,
    "sell_volume_usd": 1646429.639427602
  },
  {
    "day": "2026-04-05",
    "initiated_amount": 3556.2695189033034,
    "initiated_users": 19,
    "queue_amount": 133453.19364512412,
    "unlock_amount": 3448.1349174666275,
    "vvv_price_usd": null,
    "trade_volume_usd": 8998736.70162374,
    "staked_amount": 102534.56429072084,
    "staked_users": 253,
    "buy_volume_usd": 4495667.134857826,
    "sell_volume_usd": 4503069.566765913
  },
  {
    "day": "2026-04-06",
    "initiated_amount": 6116.5341056080915,
    "initiated_users": 19,
    "queue_amount": 136121.59283326557,
    "unlock_amount": 7429.140195367652,
    "vvv_price_usd": null,
    "trade_volume_usd": 8635793.024644762,
    "staked_amount": 75127.35916908995,
    "staked_users": 328,
    "buy_volume_usd": 4019104.6293695313,
    "sell_volume_usd": 4616688.395275237
  },
  {
    "day": "2026-04-07",
    "initiated_amount": 38250.791754658116,
    "initiated_users": 13,
    "queue_amount": 166943.244392556,
    "unlock_amount": 12307.123016427158,
    "vvv_price_usd": null,
    "trade_volume_usd": 9044420.858666841,
    "staked_amount": 70435.46395632224,
    "staked_users": 264,
    "buy_volume_usd": 4460500.528856275,
    "sell_volume_usd": 4583920.329810585
  },
  {
    "day": "2026-04-08",
    "initiated_amount": 3225.106237867078,
    "initiated_users": 14,
    "queue_amount": 157861.22761399593,
    "unlock_amount": 23758.584388912856,
    "vvv_price_usd": null,
    "trade_volume_usd": 4730262.272270586,
    "staked_amount": 23746.52601973593,
    "staked_users": 224,
    "buy_volume_usd": 2421287.170528195,
    "sell_volume_usd": 2308975.1017423975
  }
]